pymysqlpool/__init__.py
pymysqlpool/connection.py
pymysqlpool/pool.py
pymysqlpool_dd-0.1.dist-info/DESCRIPTION.rst
pymysqlpool_dd-0.1.dist-info/METADATA
pymysqlpool_dd-0.1.dist-info/RECORD
pymysqlpool_dd-0.1.dist-info/WHEEL
pymysqlpool_dd-0.1.dist-info/metadata.json
pymysqlpool_dd-0.1.dist-info/top_level.txt
