Metadata-Version: 2.0
Name: pymysqlpool-dd
Version: 0.1
Summary: MySQL connection pool utility.
Home-page: https://github.com/waipbmtd/pymysqlpool
Author: Devin
Author-email: waipbmtd@gmail.com
License: MIT
Platform: UNKNOWN
Requires: pymysql
